{
  "pages": [
    {
      "name": "index",
      "path": "pages/index/index",
      "style": {
        "navigationBarTitleText": "首页"
      }
    }
  ],
  "subPackages": [
    {
      "root": "pages/test",
      "pages": [
        {
          "name": "test",
          "path": "test",
          "style": {
            "navigationBarTitleText": "测试"
          }
        }
      ]
    }
  ],
  "globalStyle": {
    "navigationBarTextStyle": "black",
    "navigationBarTitleText": "uni-app",
    "navigationBarBackgroundColor": "#F8F8F8",
    "backgroundColor": "#F8F8F8"
  }
}
